README.md
setup.cfg
setup.py
nbeats_forecast/__init__.py
nbeats_forecast/nbeats_forecast.py
nbeats_forecast.egg-info/PKG-INFO
nbeats_forecast.egg-info/SOURCES.txt
nbeats_forecast.egg-info/dependency_links.txt
nbeats_forecast.egg-info/requires.txt
nbeats_forecast.egg-info/top_level.txt