Metadata-Version: 2.1
Name: nbeats-forecast
Version: 1.3.6
Summary: This library uses nbeats-pytorch as base and simplifies the task of univariate time series forecasting using N-BEATS by providing a interface similar to scikit-learn and keras.
Home-page: https://github.com/amitesh863/nbeats_forecast
Author: Amitesh Sharma
Author-email: amitesh863@gmail.com
License: MIT
Download-URL: https://github.com/amitesh863/nbeats_forecast/archive/1.3.6.tar.gz
Keywords: nbeats,timeseries,forecast,nueral beats,univariate timeseries forecast ,timeseries forecast,univariate timeseries forecast
Platform: UNKNOWN
Classifier: Development Status :: 5 - Production/Stable
Classifier: Topic :: Software Development :: Build Tools
Classifier: License :: OSI Approved :: MIT License
Requires-Python: >=3.6
